{
  "แกง": [
    "แกงเขียวหวาน",
    "แกงมัสมั่น",
    "แกงกะหรี่",
    "แกงจืด",
    "แกงส้ม",
    "แกงป่า",
    "แกงเทโพ",
    "ข้าวราดแกง",
    "ข้าวแกง"
  ],
  "ข้าว": [
    "ข้าวผัด",
    "ข้าวมันไก่",
    "ข้าวหมูแดง",
    "ข้าวหมูกรอบ",
    "ข้าวเหนียวหมูปิ้ง",
    "ข้าวต้ม",
    "ข้าวราดแกง",
    "ข้าวแกง"
  ],
  "ก๋วยเตี๋ยว": [
    "ก๋วยเตี๋ยวเรือ",
    "ก๋วยเตี๋ยวหมูตุ๋น",
    "ก๋วยเตี๋ยวเนื้อ",
    "เส้นเล็ก",
    "เส้นใหญ่",
    "บะหมี่",
    "ก๋วยเตี๋ยว",
    "กวยเตี๋ยว",
    "ก๋วยเตียว"
  ],
  "ของหวาน": [
    "ลอดช่อง",
    "ข้าวเหนียวมะม่วง",
    "บัวลอย",
    "ทับทิมกรอบ",
    "สังขยา",
    "ไอติม"
  ],
  "เครื่องดื่ม": [
    "ชาไทย",
    "กาแฟ",
    "ชาเขียว",
    "น้ำผลไม้",
    "สมูทตี้",
    "คาเฟ่",
    "coffee",
    "แซดโพลคาเฟ่",
    "เบียร์โภชนา"
  ],
  "ทอด": [
    "ไก่ทอด",
    "หมูทอด",
    "ปลาทอด",
    "ไข่เจียว",
    "ไข่ดาว"
  ],
  "ยำ": [
    "ยำวุ้นเส้น",
    "ยำรวมมิตร",
    "ยำทะเล",
    "ยำแซ่บ",
    "ยำหมูยอ"
  ],
  "ผัด": [
    "ผัดไทย",
    "ผัดกะเพรา",
    "ผัดซีอิ๊ว",
    "ผัดพริกเผา",
    "ผัดผงกะหรี่"
  ],
  "เจ": [
    "อาหารเจ",
    "เจ",
    "ข้าวราดแกงเจ"
  ],
  "มังสวิรัติ": [
    "อาหารมังสวิรัติ",
    "มัง",
    "vegetarian"
  ],
  "บุฟเฟ่ต์": [
    "บุฟเฟ่ต์",
    "บุฟเฟต์",
    "buffet",
    "เกรท ฮาร์เบอร์",
    "เท็นโจ"
  ],
  "ฟาสต์ฟู้ด": [
    "FastFood",
    "Fast Food",
    "เบียร์โภชนา"
  ],
  "คาเฟ่": [
    "Cafe",
    "แซดโพลคาเฟ่",
    "กาแฟ",
    "ชา",
    "ขนม"
  ]
}
